scan/__init__.py
scan/blocks.py
scan/config.py
scan/directory.py
scan/http.py
scan/span.py
scan/stripe.py
scan/ui.py
scan/utils.py
Superior_Cache_ANalyzer-3.3.7.post3.dist-info/LICENSE
Superior_Cache_ANalyzer-3.3.7.post3.dist-info/METADATA
Superior_Cache_ANalyzer-3.3.7.post3.dist-info/NOTICE
Superior_Cache_ANalyzer-3.3.7.post3.dist-info/WHEEL
Superior_Cache_ANalyzer-3.3.7.post3.dist-info/entry_points.txt
Superior_Cache_ANalyzer-3.3.7.post3.dist-info/top_level.txt
Superior_Cache_ANalyzer-3.3.7.post3.dist-info/RECORD
