Metadata-Version: 2.1
Name: Superior-Cache-ANalyzer
Version: 3.3.7.post3
Summary: An analysis tool for Apache Traffic Server caches.
Home-page: https://github.com/comcast/Superior-Cache-ANalyzer
Author: Brennan Fieck
Author-email: Brennan_WilliamFieck@comcast.com
License: UNKNOWN
Keywords: Apache traffic server ats cache analysis
Platform: UNKNOWN
Classifier: Development Status :: 4 - Beta
Classifier: Intended Audience :: Telecommunications Industry
Classifier: Intended Audience :: Developers
Classifier: Intended Audience :: Information Technology
Classifier: Topic :: Internet
Classifier: Topic :: Internet :: Log Analysis
Classifier: Topic :: Internet :: WWW/HTTP
Classifier: Topic :: Scientific/Engineering :: Information Analysis
Classifier: Topic :: System :: Logging
Classifier: Topic :: Utilities
Classifier: License :: Other/Proprietary License
Classifier: Environment :: Console
Classifier: Operating System :: POSIX :: Linux
Classifier: Programming Language :: Python :: Implementation :: CPython
Classifier: Programming Language :: Python :: Implementation :: PyPy
Classifier: Programming Language :: Python :: 3 :: Only
Classifier: Programming Language :: Python :: 3.4
Classifier: Programming Language :: Python :: 3.5
Classifier: Programming Language :: Python :: 3.6
Classifier: Programming Language :: Python :: 3.7
Requires-Python: ~=3.4
Requires-Dist: setuptools
Requires-Dist: typing
Requires-Dist: readline
Requires-Dist: numpy
Requires-Dist: psutil
